file_text_extractor/__init__.py
file_text_extractor/file_extractor.py
file_text_extractor/extractors/__init__.py
file_text_extractor/extractors/docx_extractor.py
file_text_extractor/extractors/gcs_extractor.py
file_text_extractor/extractors/pdf_extractor.py
file_text_extractor/extractors/txt_extractor.py
file_text_extractor-0.1.dist-info/METADATA
file_text_extractor-0.1.dist-info/WHEEL
file_text_extractor-0.1.dist-info/top_level.txt
file_text_extractor-0.1.dist-info/RECORD
