Metadata-Version: 2.1
Name: file_text_extractor
Version: 0.1
Summary: A package to extract text from various file formats including PDF and DOCX.
Author: Sanjana Jain
Author-email: sanjana.jain@skillsbridge.ai
Classifier: Programming Language :: Python :: 3
Classifier: License :: OSI Approved :: MIT License
Classifier: Operating System :: OS Independent
Requires-Python: >=3.6
Requires-Dist: PyMuPDF
Requires-Dist: python-docx
Requires-Dist: google-cloud-storage
